atomium/__init__.py
atomium/base.py
atomium/data.py
atomium/mmcif.py
atomium/mmtf.py
atomium/pdb.py
atomium/structures.py
atomium/utilities.py
atomium-1.0.11.dist-info/LICENSE
atomium-1.0.11.dist-info/METADATA
atomium-1.0.11.dist-info/WHEEL
atomium-1.0.11.dist-info/top_level.txt
atomium-1.0.11.dist-info/RECORD
