Metadata-Version: 2.1
Name: atomium
Version: 1.0.11
Summary: A molecular modeller and file parser.
Home-page: https://atomium.samireland.com
Author: Sam Ireland
Author-email: mail@samireland.com
License: MIT
Keywords: chemistry bioinformatics proteins biochemistry molecules PDB MMCIF CIF MMTF
Platform: UNKNOWN
Classifier: Development Status :: 4 - Beta
Classifier: Intended Audience :: Science/Research
Classifier: License :: OSI Approved :: MIT License
Classifier: Topic :: Scientific/Engineering :: Chemistry
Classifier: Programming Language :: Python :: 3
Classifier: Programming Language :: Python :: 3.6
Classifier: Programming Language :: Python :: 3.7
Classifier: Programming Language :: Python :: 3.8
Classifier: Programming Language :: Python :: 3.9
Requires-Python: !=2.*, !=3.0.*, !=3.1.*, !=3.2.*, !=3.3.*, !=3.4.*, !=3.5.*
Requires-Dist: numpy
Requires-Dist: requests
Requires-Dist: rmsd
Requires-Dist: paramiko
Requires-Dist: msgpack
Requires-Dist: valerius
